podgrab.py
podgrab-0.1.3.dist-info/METADATA
podgrab-0.1.3.dist-info/WHEEL
podgrab-0.1.3.dist-info/entry_points.txt
podgrab-0.1.3.dist-info/RECORD
