Metadata-Version: 2.1
Name: podgrab
Version: 0.1.3
Summary: CLI tool for downloading and transcribing podcasts.
License: MIT
Author: Kasper Junge
Author-email: kasperjuunge@gmail.com
Requires-Python: >=3.11,<4.0
Classifier: License :: OSI Approved :: MIT License
Classifier: Programming Language :: Python :: 3
Classifier: Programming Language :: Python :: 3.11
Classifier: Programming Language :: Python :: 3.12
Classifier: Programming Language :: Python :: 3.13
Requires-Dist: feedparser (>=6.0.11,<7.0.0)
Requires-Dist: openai-whisper (>=20240930,<20240931)
Requires-Dist: requests (>=2.32.3,<3.0.0)
Requires-Dist: rich (>=13.9.4,<14.0.0)
Requires-Dist: torch (>=2.5.1,<3.0.0)
Requires-Dist: torchaudio (>=2.5.1,<3.0.0)
Requires-Dist: torchvision (>=0.20.1,<0.21.0)
Requires-Dist: tqdm (>=4.67.0,<5.0.0)
Requires-Dist: typer (>=0.13.0,<0.14.0)
